<items>
    <item>
        <key>###H2###</key>
        <val>PADI 水肺潛水課程預約表</val>
    </item>
    <item>
        <key>###deposit dt###</key>
        <val>You will receive a PayPal deposit request from SEASIR LTD. account, to secure your booking please make your deposit of JPY3,000 per person within 3 days start from the day you receive deposit request from our PayPal account, or within 24 hours if your booking request is less than 3 days notice from the departure date. All booking request will cancel if no deposit receive.</val>
    </item>
    <item>
        <key>###Open water Diver###</key>
        <val><![CDATA[開放水域水肺潛水員<br>Open water Diver]]></val>
    </item>
    <item>
        <key>###Advanced Diver###</key>
        <val><![CDATA[進階水肺潛水員<br>Advanced Diver]]></val>
    </item>
    <item>
        <key>###Rescue Diver###</key>
        <val><![CDATA[救援潛水員<br>Rescue Diver]]></val>
    </item>
    <item>
        <key>###Diving Courses###</key>
        <val>潛水課程</val>
    </item>
    <item>
        <key>###Diver Information###</key>
        <val>Diver Information</val>
    </item>
    <item>
        <key>###diving manual lang###</key>
        <val>潛水教材的語言</val>
    </item>
    <item>
        <key>###training lang###</key>
        <val>教學的語言</val>
    </item>
    <item>
        <key>###Choose your language###</key>
        <val>選擇語言</val>
    </item>
    <item>
        <key>###English###</key>
        <val>英語</val>
    </item>
    <item>
        <key>###Chinese###</key>
        <val>中文</val>
    </item>
    <item>
        <key>###Japanese###</key>
        <val>日語</val>
    </item>
    <item>
        <key>###I would like bulabula###</key>
        <val>我希望的課程日期 : </val>
    </item>
    <item>
        <key>###Date of Course###</key>
        <val>課程日期</val>
    </item>
    <item>
        <key>###Date of Course note###</key>
        <val>“PADI水肺潛水後行程指導”建議您在一次潛水結束的12小時後再搭乘飛機，或數次潛水結束的18小時後再搭乘飛機。 (盡可能24小時後再搭乘)</val>
    </item>
    <item>
        <key>###Check in Date###</key>
        <val>入住時間</val>
    </item>
    <item>
        <key>###Check out Date###</key>
        <val>退房時間</val>
    </item>
    <item>
        <key></key>
        <val></val>
    </item>
</items>
